subspyces/__init__.py
subspyces/core/__init__.py
subspyces/core/vector_space.py
subspyces/generators/__init__.py
subspyces/generators/abstract_generator.py
subspyces/generators/identity_generator.py
subspyces/generators/pca_generator.py
subspyces/methods/__init__.py
subspyces/methods/abstract_method.py
subspyces/methods/subspace_method.py
subspyces/metrics/__init__.py
subspyces/metrics/cosine_canonical_angles.py
subspyces/metrics/cosine_similarity.py
subspyces/metrics/structure_similarity.py
subspyces/transform/__init__.py
subspyces/transform/abstract_transform.py
subspyces/transform/ipca_transform.py
subspyces/transform/pca_transform.py
subspyces/utils/__init__.py
subspyces/utils/vizualize_images.py
subspyces-0.0.5.dist-info/LICENSE
subspyces-0.0.5.dist-info/METADATA
subspyces-0.0.5.dist-info/WHEEL
subspyces-0.0.5.dist-info/top_level.txt
subspyces-0.0.5.dist-info/RECORD
